{
  "id": "09_PRI_LCA",
  "code": "09-PRI-LCA",
  "gradeLevel": "PRI",
  "subject": "LCA",
  "title": {
    "es": "Reflexionar sobre el funcionamiento de la lengua y sus usos mediante la comparación de palabras y enunciados para mejorar las destrezas de producción y comprensión.",
    "eu": "Hizkuntzaren funtzionamenduaz eta erabilerez hausnartzea, hitzak eta esaldiak alderatuz, ekoizpen eta ulermen trebetasunak hobetzeko.",
    "en": "Reflect on how language works and its uses by comparing words and sentences in order to improve production and comprehension skills.",
    "la": "De functione linguae et usibus eius reflectere verba et sententias comparans ut facultates productionis et comprehensionis meliorem."
  },
  "duaAdaptations": {
    "7.1": {
      "text": {
        "es": "",
        "eu": "",
        "en": "",
        "la": ""
      },
      "webTools": []
    },
    "7.2": {
      "text": {
        "es": "",
        "eu": "",
        "en": "",
        "la": ""
      },
      "webTools": []
    },
    "7.3": {
      "text": {
        "es": "",
        "eu": "",
        "en": "",
        "la": ""
      },
      "webTools": []
    },
    "7.4": {
      "text": {
        "es": "",
        "eu": "",
        "en": "",
        "la": ""
      },
      "webTools": []
    },
    "8.1": {
      "text": {
        "es": "",
        "eu": "",
        "en": "",
        "la": ""
      },
      "webTools": []
    },
    "8.2": {
      "text": {
        "es": "",
        "eu": "",
        "en": "",
        "la": ""
      },
      "webTools": []
    },
    "8.3": {
      "text": {
        "es": "",
        "eu": "",
        "en": "",
        "la": ""
      },
      "webTools": []
    },
    "8.4": {
      "text": {
        "es": "",
        "eu": "",
        "en": "",
        "la": ""
      },
      "webTools": []
    },
    "8.5": {
      "text": {
        "es": "",
        "eu": "",
        "en": "",
        "la": ""
      },
      "webTools": []
    },
    "9.1": {
      "text": {
        "es": "",
        "eu": "",
        "en": "",
        "la": ""
      },
      "webTools": []
    },
    "9.2": {
      "text": {
        "es": "",
        "eu": "",
        "en": "",
        "la": ""
      },
      "webTools": []
    },
    "9.3": {
      "text": {
        "es": "",
        "eu": "",
        "en": "",
        "la": ""
      },
      "webTools": []
    },
    "9.4": {
      "text": {
        "es": "",
        "eu": "",
        "en": "",
        "la": ""
      },
      "webTools": []
    },
    "1.1": {
      "text": {
        "es": "",
        "eu": "",
        "en": "",
        "la": ""
      },
      "webTools": []
    },
    "1.2": {
      "text": {
        "es": "",
        "eu": "",
        "en": "",
        "la": ""
      },
      "webTools": []
    },
    "1.3": {
      "text": {
        "es": "",
        "eu": "",
        "en": "",
        "la": ""
      },
      "webTools": []
    },
    "2.1": {
      "text": {
        "es": "",
        "eu": "",
        "en": "",
        "la": ""
      },
      "webTools": []
    },
    "2.2": {
      "text": {
        "es": "",
        "eu": "",
        "en": "",
        "la": ""
      },
      "webTools": []
    },
    "2.3": {
      "text": {
        "es": "",
        "eu": "",
        "en": "",
        "la": ""
      },
      "webTools": []
    },
    "2.4": {
      "text": {
        "es": "",
        "eu": "",
        "en": "",
        "la": ""
      },
      "webTools": []
    },
    "2.5": {
      "text": {
        "es": "",
        "eu": "",
        "en": "",
        "la": ""
      },
      "webTools": []
    },
    "3.1": {
      "text": {
        "es": "",
        "eu": "",
        "en": "",
        "la": ""
      },
      "webTools": []
    },
    "3.2": {
      "text": {
        "es": "",
        "eu": "",
        "en": "",
        "la": ""
      },
      "webTools": []
    },
    "3.3": {
      "text": {
        "es": "",
        "eu": "",
        "en": "",
        "la": ""
      },
      "webTools": []
    },
    "3.4": {
      "text": {
        "es": "",
        "eu": "",
        "en": "",
        "la": ""
      },
      "webTools": []
    },
    "4.1": {
      "text": {
        "es": "",
        "eu": "",
        "en": "",
        "la": ""
      },
      "webTools": []
    },
    "4.2": {
      "text": {
        "es": "",
        "eu": "",
        "en": "",
        "la": ""
      },
      "webTools": []
    },
    "5.1": {
      "text": {
        "es": "",
        "eu": "",
        "en": "",
        "la": ""
      },
      "webTools": []
    },
    "5.2": {
      "text": {
        "es": "",
        "eu": "",
        "en": "",
        "la": ""
      },
      "webTools": []
    },
    "5.3": {
      "text": {
        "es": "",
        "eu": "",
        "en": "",
        "la": ""
      },
      "webTools": []
    },
    "5.4": {
      "text": {
        "es": "",
        "eu": "",
        "en": "",
        "la": ""
      },
      "webTools": []
    },
    "6.1": {
      "text": {
        "es": "",
        "eu": "",
        "en": "",
        "la": ""
      },
      "webTools": []
    },
    "6.2": {
      "text": {
        "es": "",
        "eu": "",
        "en": "",
        "la": ""
      },
      "webTools": []
    },
    "6.3": {
      "text": {
        "es": "",
        "eu": "",
        "en": "",
        "la": ""
      },
      "webTools": []
    },
    "6.4": {
      "text": {
        "es": "",
        "eu": "",
        "en": "",
        "la": ""
      },
      "webTools": []
    },
    "6.5": {
      "text": {
        "es": "",
        "eu": "",
        "en": "",
        "la": ""
      },
      "webTools": []
    }
  }
}